{
  "data": {
    "region": "kr",
    "slug": "analysis-of-harmonics-in-the-korean-power-system-kr",
    "title": "Analysis of Harmonics in the Korean Power System: - Carelabs South Korea",
    "metaTitle": "Analysis of Harmonics in the Korean Power System: - Carelabs South Korea | Carelabs",
    "metaDescription": "Manage Cookie Consent To provide the best experiences, we use technologies like cookies to store and/or access device information. Consenting to these technol",
    "excerpt": "Manage Cookie Consent To provide the best experiences, we use technologies like cookies to store and/or access device information. Consenting to these technologies will allow us to process data such as browsing behavior.",
    "body": "[Home](https://carelabz.com/kr/) /[Blog](https://carelabz.com/kr/blog) /[Analysis of Harmonics in the Korean Power System:](https://carelabz.com/kr/analysis-of-harmonics-in-the-korean-power-system/)\n\n## Analysis of Harmonics in the Korean Power System:\n\nPower is a crucial part of daily life in the modern world. Most objects we use daily are powered in some way. We must make use of the most innovative power technology available to supply people with electricity in a safe and fair manner. Harmonics raise the circuit’s current flow’s RMS value, which raises the loss. The electrical systems have been plagued by several issues as a result. Harmonics have an impact on the loads as well as the entire distribution system. Additionally, delicate office and manufacturing tools and equipment are vulnerable to harmonic damage. Harmonic defect cannot always be obvious right once, and it might be challenging to tell it apart from regular wear and tear.\n\n#### Table of Contents\n\n![analysis-of-harmonics-in-the-japanese-power-system-1](https://carelabz.com/kr/wp-content/uploads/2023/06/38.jpg)\n\n### Harmonic Distortion Definition:\n\nHarmonic problems may reduce the reliability of the power supply due to its tiny size. Electric current and voltage harmonics cause problems in power systems. Equipment may malfunction or fail when the power source contains numerous harmonics. Harmonics, or changes in the shape of the current waveform, are typically introduced into an electrical system by a nonlinear load. Nonlinear loads and harmonics are produced in power systems by personal computers, variable speed motors, driven motors, fax machines, laser printers, Switch-mode power supplies (SMPS), batteries, and uninterruptible power supplies (UPS).\n\nGet in Touch\n\nNewsletter\n\nEnquire\n\n![analysis-of-harmonics-in-the-japanese-power-system-2](https://carelabz.com/kr/wp-content/uploads/2023/06/221-1.jpg)\n\n### The Need for Harmonic Analysis:\n\nElectrical systems become less reliable and efficient because of harmonics. Your power system’s dependability will improve if you apply harmonic analysis to find harmonics there. Non-linear currents are created when power electronics equipment usage grows. The system needs to lead to the creation of harmonics. Equipment must be more energy efficient and use less electricity. \n\n**When did Harmonic Analysis become significant?**\n\n- The harmonic limits need to be examined if the total load or bus system readings are greater than 25% of the total load.\n- to fix harmonic-related problems, such equipment failure or damage.\n- When and how many non-linear loads will the plant be expanded?\n- When an additional capacitor bank is introduced to the electrical systems, harmonic analysis is required.\n\n![analysis-of-harmonics-in-the-japanese-power-system-2](https://carelabz.com/kr/wp-content/uploads/2023/06/221-1.jpg)\n\n![analysis-of-harmonics-in-the-japanese-power-system-3](https://carelabz.com/kr/wp-content/uploads/2023/06/281-1.jpg)\n\n| The design of the apparatus | An unhurried conclusion |\n| --- | --- |\n| The design of the apparatus Equipment that rotates | An unhurried conclusion In addition to power loss, overheating, and pulsing torque, cable resistance increases. |\n| The design of the apparatus Power lines, a switchboard, and a transformer are necessary. | An unhurried conclusion Overheating, excessive use, overloading the neutral, and power outages are indications that there is a problem. |\n| The design of the apparatus Electric capacitors | An unhurried conclusion Many current events are unintentionally happening. |\n| The design of the apparatus Electrical power | An unhurried conclusion Inadequate performance |\n| The design of the apparatus Safeguarding relays | An unhurried conclusion Rude habits and challenging travels |\n\nA sinusoidal waveform encounters a nonlinear load, causing distortion and harmonic generation in the system. The existence or absence of harmonics in a system is frequently detected through harmonic analysis.\n\n![analysis-of-harmonics-in-the-japanese-power-system-4](https://carelabz.com/kr/wp-content/uploads/2023/06/getimg_ai_img-2Cu4kGSTd93kI2uoRpD0B-1.png)\n\n### Benefits of Doing Away with Harmonics in the Power System:\n\n- By minimizing the amount of energy wasted through cables, switch gears, and safety systems, harmonic analysis lowers operational expenses. It also aids in lowering power system losses.\n- It permits the removal of large transformers, which lowers the need for cable, switchgear, and busbars by lowering the RMS current in the electrical system.\n- Performance naturally increases when losses are reduced, and the RMS current value is lowered. Harmonics cause overheating of cables, transformers, motors, and capacitors in addition to increasing losses and raising the RMS value of current. The undesirable outcomes may force you to terminate a surgery or cause you to lose money.\n\n![analysis-of-harmonics-in-the-japanese-power-system-4](https://carelabz.com/kr/wp-content/uploads/2023/06/getimg_ai_img-2Cu4kGSTd93kI2uoRpD0B-1.png)\n\n![analysis-of-harmonics-in-the-japanese-power-system-5](https://carelabz.com/kr/wp-content/uploads/2023/06/getimg_ai_img-qcYRcEtAdwJVdemlPKhEn-2.png)\n\n![analysis-of-harmonics-in-the-japanese-power-system-5](https://carelabz.com/kr/wp-content/uploads/2023/06/getimg_ai_img-qcYRcEtAdwJVdemlPKhEn-2.png)\n\n### Procedure for Conducting a Power Quality Analysis:\n\n- Make a single-line graph to display non-linear loads.\n- Keep an eye out for the connecting thread (PCC).\n- Exposes the buses inside the building that might be impacted by harmonics.\n- Gather as much data as you can on the electricity provider’s historical harmonics performance and non-linear load characteristics.\n- Using the ETAP program and the electrical system’s performance, create a model.\n- Examine the harmonics, voltage, and current distortion levels.\n- Choose a cure if the harmonic distortion is too great.\n- After implementing the mitigation strategy, do another harmonic analysis to confirm CEC compliance.\n\nCareLabs provides state-of-the-art technology to its employees so that they can guarantee the security of your electrical equipment and provide you with a safe working environment. Get a quotation now and find out more about CareLabs’ harmonics research and analysis services.\n\n## RELATED NEWS\n\n![](//carelabz.com/kr/wp-content/plugins/revslider/public/assets/assets/dummy.png)\n![](//carelabz.com/kr/wp-content/plugins/revslider/public/assets/assets/dummy.png)\nElectrical arcs can emerge when a gas is subjected to a voltage greater than its.....\n[The Significance of Arc Flash Hazard Analysis and Mitigation Techniques](https://carelabz.com/kr/the-significance-of-arc-flash-hazard-analysis-and-mitigation-techniques/)\n\n01\n05\nDiscover Our Latest News\nOur picked blog posts address current happenings. Updated technology, business, health, and lifestyle articles. Keep up with our highlighted content. \n \n \n[Read](https://carelabz.com/kr/blogs/)[Korean Arc Flash Analysis: A Comprehensive Guide](https://carelabz.com/kr/korean-arc-flash-analysis-a-comprehensive-guide/)Electrical arcs form when a gas is exposed to a voltage greater than the voltage it can......\n \n\n![harmonic-study-main-blog-2](//carelabz.com/kr/wp-content/plugins/revslider/public/assets/assets/dummy.png)\n![harmonic-study-main-blog-1](//carelabz.com/kr/wp-content/plugins/revslider/public/assets/assets/dummy.png)\nPower is a crucial component of daily existence in the modern world. The bulk.....\n[Analysis of Harmonics in the Korean Power System:](https://carelabz.com/kr/analysis-of-harmonics-in-the-korean-power-system/)\n\n02\n05\nDiscover Our Latest News\nOur picked blog posts address current happenings. Updated technology, business, health, and lifestyle articles. Keep up with our highlighted content. \n \n \n[Read](https://carelabz.com/kr/blogs/)[Why Are Harmonic Analysis and Research Crucial for Korean Businesses?](https://carelabz.com/kr/why-are-harmonic-analysis-and-research-crucial-for-korean-businesses/)Harmonics is an essential component.....\n \n\n![](//carelabz.com/kr/wp-content/plugins/revslider/public/assets/assets/dummy.png)\n![](//carelabz.com/kr/wp-content/plugins/revslider/public/assets/assets/dummy.png)\nThe quality of the power supply has an immediate impact on the functioning of.....\n[Working Principles for Power Quality in Korea](https://carelabz.com/kr/working-principles-for-power-quality-in-korea/)\n\n03\n05\nDiscover Our Latest News\nOur picked blog posts address current happenings. Updated technology, business, health, and lifestyle articles. Keep up with our highlighted content. \n \n \n[Read](https://carelabz.com/kr/blogs/)[How to Conduct a Power Quality Analysis in Korea?](https://carelabz.com/kr/how-to-conduct-a-power-quality-analysis-in-korea/)Power quality is the efficiency with which a piece of equipment utilizes the provided....\n \n\n![power-system-main-blog-2](//carelabz.com/kr/wp-content/plugins/revslider/public/assets/assets/dummy.png)\n![power-system-study-and-analysis-5](//carelabz.com/kr/wp-content/plugins/revslider/public/assets/assets/dummy.png)\nA power system analysis entails a range of.....\n[Analysis of Power System Load Flow, Short Circuit, and Relay \nCoordination](https://carelabz.com/kr/analysis-of-power-system-load-flow-short-circuit-and-relay-coordination/)\n\n04\n05\nDiscover Our Latest News\nOur picked blog posts address current happenings. Updated technology, business, health, and lifestyle articles. Keep up with our highlighted content. \n \n \n[Read](https://carelabz.com/kr/blogs/)[Why Load Flow and Short Circuit Analysis Are Important for a Korean Business?](https://carelabz.com/kr/why-load-flow-and-short-circuit-analysis-are-important-for-a-korean-business/)Everyone is aware of the significance of....\n \n\n![check-and-test-the-performance-of-electric-motors-according-to-japanese-rules-1](//carelabz.com/kr/wp-content/plugins/revslider/public/assets/assets/dummy.png)\n![motor-start-main-blog-1](//carelabz.com/kr/wp-content/plugins/revslider/public/assets/assets/dummy.png)\nIn many different applications around...\n[Check and Test the Performance of Electric Motors According to Korean Rules](https://carelabz.com/kr/check-and-test-the-performance-of-electric-motors-according-to-korean-rules/)\n\n05\n05\nDiscover Our Latest News\nOur picked blog posts address current happenings. Updated technology, business, health, and lifestyle articles. Keep up with our highlighted content. \n \n \n[Read](https://carelabz.com/kr/blogs/)[How Can the Quality and Dependability of Commercial Motors Be Evaluated?](https://carelabz.com/kr/how-can-the-quality-and-dependability-of-commercial-motors-be-evaluated/)Improving energy efficiency is the cleanest...\n\n## RELATED NEWS\n\n![arc-flash-main-blog-1](//carelabz.com/kr/wp-content/uploads/2023/06/engineer-wearing-safety-suit-near-a-electrical-pan-7-230x192.png)\nKorean Arc Flash Analysis: A Comprehensive Guide\nElectrical arcs form when a gas is exposed to a voltage....\n[Read](https://carelabz.com/kr/korean-arc-flash-analysis-a-comprehensive-guide/) \n\n![](//carelabz.com/kr/wp-content/uploads/2023/06/engineer-wearing-safety-suit-near-a-electrical-pan-150x150.png)\nThe Significance of Arc Flash Hazard Analysis and Mitigation Techniques\nElectrical arcs can emerge when a gas is subjected to a....\n[Read](https://carelabz.com/kr/the-significance-of-arc-flash-hazard-analysis-and-mitigation-techniques/) \n\n![harmonic-study-main-blog-2](//carelabz.com/kr/wp-content/plugins/revslider/public/assets/assets/dummy.png)\nWhy Are Harmonic Analysis and Research Crucial for Korean Businesses?\nHarmonics is an essential component of a power system.....\n[Read](https://carelabz.com/kr/why-are-harmonic-analysis-and-research-crucial-for-korean-businesses/) \n\n![harmonic-study-main-blog-1](//carelabz.com/kr/wp-content/plugins/revslider/public/assets/assets/dummy.png)\nAnalysis of Harmonics in the Korean Power System:\nPower is a crucial component of daily existence in the modern....\n[Read](https://carelabz.com/kr/analysis-of-harmonics-in-the-korean-power-system/) \n\n![power-quality-main-blog-1](//carelabz.com/kr/wp-content/plugins/revslider/public/assets/assets/dummy.png)\nHow to Conduct a Power Quality Analysis in Korea?\nPower quality is the efficiency with which a piece of equipment.....\n[Read](https://carelabz.com/kr/how-to-conduct-a-power-quality-analysis-in-korea/) \n\n![power-quality-main-blog-2](//carelabz.com/kr/wp-content/plugins/revslider/public/assets/assets/dummy.png)\nWorking Principles for Power Quality in Korea\nThe quality of the power supply has an immediate impact on the....\n[Read](https://carelabz.com/kr/working-principles-for-power-quality-in-korea/) \n\n![power-system-main-blog-1](//carelabz.com/kr/wp-content/plugins/revslider/public/assets/assets/dummy.png)\nWhy Load Flow and Short Circuit Analysis Are Important for a Korean Business?\nEveryone is aware of the significance of energy to our way...\n[Read](https://carelabz.com/kr/why-load-flow-and-short-circuit-analysis-are-important-for-a-korean-business/) \n\n![power-system-main-blog-2](//carelabz.com/kr/wp-content/plugins/revslider/public/assets/assets/dummy.png)\nAnalysis of Power System Load Flow, Short Circuit, and Relay Coordination\nA power system analysis entails a range of technical assessments....\n[Read](https://carelabz.com/kr/analysis-of-power-system-load-flow-short-circuit-and-relay-coordination/) \n\n![motor-start-main-blog-1](//carelabz.com/kr/wp-content/uploads/2023/06/81-150x150.jpg)\nHow Can the Quality and Dependability of Commercial Motors Be Evaluated?\nImproving energy efficiency is the cleanest, most cost-effective......\n[Read](https://carelabz.com/kr/how-can-the-quality-and-dependability-of-commercial-motors-be-evaluated/) \n\n![motor-start-main-blog-2](//carelabz.com/kr/wp-content/uploads/2023/06/image-150x150.png)\nCheck and Test the Performance of Electric Motors According to Korean Rules\nIn many different applications around the world, industrial......\n[Read](https://carelabz.com/kr/check-and-test-the-performance-of-electric-motors-according-to-korean-rules/)\n\n### Leave a Reply [Cancel reply](/kr/analysis-of-harmonics-in-the-korean-power-system/#respond)",
    "author": "admin",
    "category": "Power Systems",
    "tags": [],
    "publishedDate": "2023-06-22T05:51:10Z",
    "heroImage": "https://rational-cheese-8e8c4f80ea.media.strapiapp.com/kr_blog_analysis_of_harmonics_in_the_korean_power_system_19fda2eb2b.jpg",
    "heroImageAlt": "Analysis of Harmonics in the Korean Power System: - Carelabs South Korea",
    "seoKeywords": [
      "analysis of harmonics in the korean power system: - carelabs south korea",
      "analysis of harmonics in the korean power system: - carelabs south korea KR"
    ],
    "publishedAt": null
  },
  "_source": {
    "wp_url": "https://carelabz.com/kr/analysis-of-harmonics-in-the-korean-power-system/",
    "wp_screenshot": "tests/screenshots/wp-kr-blog/analysis-of-harmonics-in-the-korean-power-system.png",
    "body_chars": 14158
  }
}