{
  "data": {
    "region": "tr",
    "slug": "principles-of-work-on-saudi-arabia-power-quality-tr",
    "title": "Power Quality Principles in Turkey | Carelabs Insights",
    "metaTitle": "Power Quality Principles in Turkey | Carelabs Insights | Carelabs",
    "metaDescription": "Understand the key power quality principles in Turkey with Carelabs. Improve energy efficiency, reduce electrical disturbances.",
    "excerpt": "Understand the key power quality principles in Turkey with Carelabs. Improve energy efficiency, reduce electrical disturbances.",
    "body": "## Power Quality Analysis\n\n## Principles of Work on Turkish Power Quality:\n\nThe fundamental functionality and efficacy of devices connected to the distribution network are directly influenced by the quality of the power supply. It is believed that the equipment functions as intended and has a lifespan roughly equivalent to the specified value. Additionally, it is anticipated that the network will be stable enough to prevent problems such as subpar output and missing functionality. There are numerous issues with the power quality of the electricity system. Regardless of their duration, these power quality disruptions have the potential to cause harm to your device. Maintaining power quality is crucial for preventing equipment failure. This article will discuss the research required to assess the dependability and quality of electricity. Examining various power quality systems and methodologies for evaluating the effect and the control is the next step. In contrast to dependability, which is concerned with lengthy power disruptions, power quality disturbances have delayed effects. In other instances, however, an interruption in power quality has an immediate effect due to process delays or equipment damage. This is especially true for delays, pauses, and transitions. In certain instances, the effects of a disruption in power quality may not be immediately apparent. Equipment deterioration is one example. Consequently, equipment deterioration is left unfettered for years. In other instances, power quality issues result in additional losses that are deemed unavoidable and are therefore disregarded.\n\n![](https://carelabz.com/tr/wp-content/uploads/2023/08/visualize-a-skilled-engineer-from-carelabs-conducting-a-harmonic-study-and-analysis-at-a-commercial-933153727-1.jpg)\n\n## The Consequences of Low-Quality Electricity:\n\n## Direct financial effects include:\n\n- Production deficiencies\n- There are expenses associated with restarting a procedure.\n- Equipment damage and repair expenses\n- More challenges and delays\n- Concerns for the safety and wellbeing of individuals\n- Financial penalties related to contract violations\n- Monetary sanctions for environmental infractions\n- The disruption increased utility prices.\n\n## These are examples of indirect economic effects:\n\n- The expenses incurred by a company due to a revenue or income delay.\n- The monetary consequences of losing market share\n- What it will cost to restore brand value\n\n## The following are among the social and economic effects:\n\n- The increase in temperature within a building may be detrimental to the health, safety, or Productivity of its occupants.\n- An individual injury or concern\n- If the change in power quality passes undetected, it may result in an electrical hazard.\n\n## Understanding the Sources of Substandard Electricity:\n\nA power supply system’s voltage, frequency, and waveform are evaluated to determine its power quality. Nonetheless, power quality is affected by a number of factors. This blog discusses the following topics pertaining to the sanctity of power:\n\n1. Voltage Stability\n2. Voltage Difference\n3. Current’s Number of Syllables\n4. Alternating or Fluctuating Voltage\n5. Voltage Dips (occasionally called “sags”) and Interruptions\n6. Due to their rarity, other phenomena such as surges, transients, inter harmonics, and cacophony have received less attention.\n\n1. Voltage Stability\n\nThe magnitudes of stable-state voltage correspond to the magnitudes of sustained voltage over extended periods of time (minutes or hours). Equipment failure, an increase in energy consumption, and system malfunction are the primary effects of prolonged high voltage (overvoltage) or low voltage (undervoltage).\n\n2. Voltage Difference\n\nFrequently, unbalanced voltage is associated with increased losses, especially in induction and three-phase motors.\n\n- The results are bearing deterioration and reverse torque.\n- Stator and rotor temperatures continue to increase\n- Current installation cable carrying capacities are decreasing.\n- The neutral conductor has experienced an increase in losses.\n- The use of wires increases energy waste.\n\n3. Current’s Number of Syllables\n\nEvery energy consumer generates and introduces harmonic currents into the power grid. Alternating currents with harmonic currents have intrinsic frequencies that are multiples of 50 hertz. The most common non-linear electrical equipment that emits harmonic currents are computers, variable speed drives (VSD), and discharge lighting. Harmonic currents are especially detrimental to the installation and power distribution system. Harmonics have several negative effects, including fractured components, damaged installation parts, component loading, inefficient use of the present carrying capacity of the installation, shortened component life, and ineffectual operation of protective components.\n\n4. Alternating or Fluctuating Voltage\n\nFlicker is a modulation of the envelope of voltage waveforms. Consequently, incandescent light sources display cyclical variations in light intensity. Some individuals may experience discomfort, decreased productivity, migraines, and, in rare cases, convulsions as a result of this irregular variation in light output.\n\n5. Voltage Dips\n\nMost of the equipment is unaffected by voltage dips and interruptions; however, longer interruptions frequently result in output loss due to equipment malfunction. On occasion, it is observed that the cost of a protracted interruption is logarithmic rather than proportional to its duration. The following variables have a significant impact on the cost of a protracted interruption, according to experts:\n\n- In the manufacturing industry, the economic impact of a disruption lasting one second, one minute, or one hour is negligible.\n- The date, time, and location of the event (weekday, weekend, daytime, midnight).\n\nAEMO computes the value of customer dependability (VCR) in order to evaluate the monetary impact of outages on all customers. Even if the majority of these figures represent consumers’ willingness to pay to avoid a disruption, it is expected that this willingness to pay will correlate strongly with the actual cost. Based on these calculations, a one-second interruption costs roughly 20% less than an hour-long interruption.\n\n## How Can Issues with Power Quality Be Mitigated?\n\nCareLabs provides numerous identification and evaluation services for power quality issues. Included are the following:\n\n- This analysis is conducted in accordance with the operating conditions. The function computes system losses, voltage levels, power factor, and flow rates.\n- This method employs computer algorithms to identify and anticipate future harmonic issues. On the premise of the results, there are also proposed reduction measures.\n- Analysis of Fluctuations and Spikes explains the causes of fluctuations and surges.\n- This study will track the short-term increase and decrease in voltage, as well as its value and direction.\n- This investigation will determine the optimal reactive power at the load and distribution ends.\n- This initiative would monitor and coordinate captive electricity in order to meet demand, reduce energy surcharges, and decrease fuel consumption.\n\nUsing ETAP (Electrical Transient Analysis Program) – Electrical Transient Analysis Program software, CareLabs analyzes and evaluates power quality. The finest software available for performing calculations and simulations for all electrical system components and ensuring equipment safety. In every significant city in Turkey, including Istanbul, Ankara, Izmir, and Bursa, we conduct power quality assessments. CareLabs provides the highest quality of service to improve the dependability and quality of your electrical system. Contact us promptly to schedule an inspection of power quality or to receive a quote!\n\n## OUR\n\n## Blogs",
    "author": "admin",
    "category": "Power Systems",
    "tags": [],
    "publishedDate": "2023-08-04T04:38:19Z",
    "heroImage": "https://rational-cheese-8e8c4f80ea.media.strapiapp.com/tr_blog_principles_of_work_on_saudi_arabia_power_quality_db0de58ec8.jpg",
    "heroImageAlt": "Power Quality Principles in Turkey | Carelabs Insights",
    "seoKeywords": [
      "power quality principles in turkey | carelabs insights",
      "power quality principles in turkey | carelabs insights TR"
    ],
    "publishedAt": null
  },
  "_source": {
    "wp_url": "https://carelabz.com/tr/principles-of-work-on-saudi-arabia-power-quality/",
    "wp_screenshot": "tests/screenshots/wp-tr-blog/principles-of-work-on-saudi-arabia-power-quality.png",
    "body_chars": 7868
  }
}