{
  "data": {
    "region": "gr",
    "slug": "load-flow-short-circuit-and-relay-coordination-in-power-system-analysis-gr",
    "title": "Power System Analysis Services in Greece | Carelabs Experts",
    "metaTitle": "Power System Analysis Services in Greece | Carelabs Experts | Carelabs",
    "metaDescription": "Carelabs Greece provides expert power system analysis services. Enhance system reliability, ensure compliance, and optimize performance across your operations",
    "excerpt": "Carelabs Greece provides expert power system analysis services. Enhance system reliability, ensure compliance, and optimize performance across your operations.",
    "body": "## Load Flow, Short Circuit, and Relay Coordination in Power System Analysis\n\nIn order to provide your facility with a power system that is safe, effective, and reliable for use in both typical and abnormal circumstances, a power system analysis consists of numerous engineering assessments including the application of scientific analytic principles and techniques. The goal of a power system analysis is to comprehend how a system will function in various configurations and the impacts on the system of disturbances such as capacitor switching, the beginning of a large motor, or incident energy from an arc flash. The reliable operation of safety equipment in the case of a short circuit or if any other fault is present may also require a power system analysis. \n\nStudies of power systems are crucial for providing a steady and dependable supply of electricity. Under all operational circumstances, a well-designed power system ensures dependable operation and maximizes plant availability. Outages, flaws, inefficiencies, and impaired safety are all effects of poorly built systems. \n\n**Most or all of the following sub-studies may be included in an average power system analysis:** \n\n1. Analysis and investigation of load flow\n2. Analysis and investigation of short circuits\n3. Analysis of relay coordination\n4. Arc Flash Hazard Analysis & Study\n5. Analysis of harmonics\n6. Analysis of dynamics and transients\n7. Earthing research\n\nWe’ll examine the first three studies in this blog. and comprehend the guidelines and methods used to carry out each of these investigations.\n\n## Load Flow Analysis and Study:\n\nA load flow study examines an electrical network to ascertain the direction of power flow. It helps in assessing the power system’s operational status as well as the amount of active and reactive power generated, losses, voltage, current, and power factor. \n\n**The analysis of load flow involved the following three phases:** \n\n- Network and component modeling for power systems\n- The creation of equations for load flow.\n- Using numerical techniques to solve the equations relating load and flow.\n\n**Three methods are used to calculate the power system data:** \n\n- The Gauss-Seidel System is one of the most used analytical techniques. This approach has the advantages of being simple to use, requiring little computational power, and finishing quicker. However, more iterations are required due to the slow convergence. As the number of buses rises, so does the number of iterations.\n- The Newton-Raphson method is more sophisticated and uses quadratic convergence, which is helpful in complex situations. This method uses less processing power since it requires fewer iterations to reach convergence. It is even more exact since it is less susceptible to complicated factors like regulating transformers or slack bus selection. One drawback is that programming can be challenging and requires a lot of machine memory.\n- Another method for performing load flow analysis is the Fast Decoupled Load Flow System (FDLF). This method’s main advantage is that it uses less computer memory. It is a popular substitute for real-time power grid management since the calculation speed is 5 times faster than the Newton-Raphson method. This piece of software can only be used in certain situations. It is therefore more challenging to adapt it to consider other issues like flow or system protection in the power industry.\n\n## Short Circuit Analysis & Study:\n\nOne or more of the following types of short circuits will be included in a short circuit analysis: \n\n- Line-to-line fault, which occurs when two phases are simultaneously shorted out.\n- One phase only contacts the ground in a single line-to-ground fault.\n- Double line-to-ground fault, in which the ground and both phases are simultaneously shorted.\n- The three phases are all shorted together in a three-phase fault.\n\nOnce the type of defect is identified, creating a one-line schematic of the power distribution system will be simpler. Calculate short circuits using the generated single-line diagram and an impedance diagram with numerical values for the utility source, transformer, and conductor in relation to the usable voltage of each component. Calculated values include short circuit current, transformer multiplier, and full-load amps. In order to verify that the power distribution system is outfitted with the proper safety devices at various locations to prevent danger and downtime, it is crucial to compare the acquired results with the equipment ratings.\n\n## Analysis of Relay Coordination:\n\nSince coordination systems guarantee quick, dependable, and selective relay operations to isolate the fault, relay coordination is an essential component of power system protection architecture. The degree to which overcurrent protective devices are necessary for the power system is determined by the coordination analysis. It also helps in figuring out the requirements, arrangements, and dimensions necessary to strike a compromise between equipment security and restricted system function. \n\nWith the use of power system software like ETAP, data collection operations are carried out to simulate the system. Short circuit analysis is done initially, then the fault currents at each electrical point in the system are measured. The effects of system equipment failures are then minimized by selecting and calibrating the protective devices. To identify areas of coordination failure, the time-current characteristic curves of the protective device are measured and compared. To achieve selective and dependable operation of protective devices, adjustments are performed as necessary.\n\n## Power system analysis benefits include:\n\n- Reliability of the power system is increased.\n- Using equipment with the proper rated power system.\n- Increased safety and decreased danger from electrical hazards.\n- Adherence to applicable regulatory requirements and electrical installation codes.\n- The suggestion of alternative techniques to enhance the system’s performance and dependability.\n- For any upcoming inspections, a record of the current state of the power system is made.\n\nIn order to monitor the voltage at different buses as well as the actual and reactive power flow between buses, analyze the system under various fault conditions, and determine the system’s resilience to minor and significant disturbances, Care Labs offers Load Flow study & analysis, Short Circuit study & analysis, and Relay coordination analysis. \n\nContact us or request a quote to get a power system analysis for your business in Greece. Within 24 hours, one of our support staff members will respond.\n\n![Motor Start Analysis in Greece](data:image/gif;base64,R0lGODlhAQABAAAAACH5BAEKAAEALAAAAAABAAEAAAICTAEAOw==)\n\n#### [Motor Start Analysis in Greece](https://carelabz.com/gr/motor-start-analysis-in-greece/ \"Motor Start Analysis in Greece\")\n\n![Power System Study & Analysis in Greece](data:image/gif;base64,R0lGODlhAQABAAAAACH5BAEKAAEALAAAAAABAAEAAAICTAEAOw==)\n\n#### [Power System Study & Analysis in Greece](https://carelabz.com/gr/power-system-study-and-analysis-in-greece/ \"Power System Study & Analysis in Greece\")\n\n![Power Quality Analysis in Greece](data:image/gif;base64,R0lGODlhAQABAAAAACH5BAEKAAEALAAAAAABAAEAAAICTAEAOw==)\n\n#### [Power Quality Analysis in Greece](https://carelabz.com/gr/power-quality-analysis-in-greece/ \"Power Quality Analysis in Greece\")\n\n![Harmonic Study & Analysis in Greece](data:image/gif;base64,R0lGODlhAQABAAAAACH5BAEKAAEALAAAAAABAAEAAAICTAEAOw==)\n\n#### [Harmonic Study & Analysis in Greece](https://carelabz.com/gr/harmonic-study-and-analysis-in-greece/ \"Harmonic Study & Analysis in Greece\")\n\n![Arc Flash Study in Greece](data:image/gif;base64,R0lGODlhAQABAAAAACH5BAEKAAEALAAAAAABAAEAAAICTAEAOw==)\n\n#### [Arc Flash Study in Greece](https://carelabz.com/gr/arc-flash-study-in-greece/ \"Arc Flash Study in Greece\")\n\n## Share Post\n\n## Related Posts\n\n- [How to Conduct Power Quality Analysis in Greece](https://carelabz.com/gr/how-to-conduct-power-quality-analysis-in-greece-2/)\n- [Power Quality Working Principles in Greece](https://carelabz.com/gr/power-quality-working-principles-in-greece/)\n- [The Importance of Load Flow and Short Circuit Analysis for a Greek Business](https://carelabz.com/gr/importance-of-load-flow-and-short-circuit-analysis-for-a-greek-business/)\n- [Test and Verify Electrical Motor Efficiency in accordance with Greek Guidelines](https://carelabz.com/gr/test-and-verifelectrical-motor-efficiency-in-accordance-with-greek-guidelines/)\n- [How to evaluate efficiency and dependability of commercial motors?](https://carelabz.com/gr/how-to-evaluate-the-efficiency-and-dependability-of-commercial-motors/)\n- [Arc Flash Analysis in Greece: A Step-by-Step Guide](https://carelabz.com/gr/arc-flash-analysis-in-greece-a-step-by-step-guide/)\n- [Load Flow, Short Circuit, and Relay Coordination in Power System Analysis](https://carelabz.com/gr/load-flow-short-circuit-and-relay-coordination-in-power-system-analysis/)\n- [Why is Harmonic Analysis and Study Important for Greek Businesses?](https://carelabz.com/gr/why-is-harmonic-analysis-and-study-important-for-greek-businesses/)\n- [Importance of Arc Flash Hazard Analysis and Mitigation Methods](https://carelabz.com/gr/importance-of-arc-flash-hazard-analysis-and-mitigation-methods/)\n- [Harmonic Analysis in Power System in Greece](https://carelabz.com/gr/harmonic-analysis-in-power-system-in-greece/)",
    "author": "admin",
    "category": "Power Systems",
    "tags": [],
    "publishedDate": "2022-11-22T04:49:13Z",
    "heroImage": "https://rational-cheese-8e8c4f80ea.media.strapiapp.com/gr_blog_load_flow_short_circuit_and_relay_coordination_in_power_system_analysis_30e03eac01.jpg",
    "heroImageAlt": "Power System Analysis Services in Greece | Carelabs Experts",
    "seoKeywords": [
      "power system analysis services in greece | carelabs experts",
      "power system analysis services in greece | carelabs experts GR"
    ],
    "publishedAt": null
  },
  "_source": {
    "wp_url": "https://carelabz.com/gr/load-flow-short-circuit-and-relay-coordination-in-power-system-analysis/",
    "wp_screenshot": "tests/screenshots/wp-gr-blog/load-flow-short-circuit-and-relay-coordination-in-power-system-analysis.png",
    "body_chars": 9458
  }
}